tap2talk/__init__.py
tap2talk/__main__.py
tap2talk/app.py
tap2talk/config.py
tap2talk/log.py
tap2talk/paths.py
tap2talk/service.py
tap2talk/audio/__init__.py
tap2talk/audio/recorder.py
tap2talk/hotkeys/__init__.py
tap2talk/hotkeys/base.py
tap2talk/hotkeys/mac.py
tap2talk/hotkeys/pynput_listener.py
tap2talk/hotkeys/win.py
tap2talk/insert/__init__.py
tap2talk/insert/clipboard.py
tap2talk/insert/mac.py
tap2talk/insert/win.py
tap2talk/transcribe/__init__.py
tap2talk/transcribe/groq_client.py
tap2talk/ui/__init__.py
tap2talk/ui/native_overlay.py
tap2talk/ui/overlay.py
tap2talk/ui/tray.py
tap2talk-0.2.0.dist-info/licenses/LICENSE
tap2talk-0.2.0.dist-info/METADATA
tap2talk-0.2.0.dist-info/WHEEL
tap2talk-0.2.0.dist-info/entry_points.txt
tap2talk-0.2.0.dist-info/top_level.txt
tap2talk-0.2.0.dist-info/RECORD
