Metadata-Version: 2.4
Name: tap2talk
Version: 0.2.0
Summary: Voice transcription desktop app - Double-tap Ctrl to start/stop recording
Author: Tap2Talk
Author-email: unclecode <unclecode@kidocode.com>
License: MIT
Project-URL: Homepage, https://github.com/unclecode/tap2talk
Project-URL: Repository, https://github.com/unclecode/tap2talk
Project-URL: Issues, https://github.com/unclecode/tap2talk/issues
Keywords: voice,transcription,macos,desktop,groq,whisper
Classifier: Development Status :: 4 - Beta
Classifier: Environment :: MacOS X
Classifier: Intended Audience :: End Users/Desktop
Classifier: License :: OSI Approved :: MIT License
Classifier: Operating System :: MacOS
Classifier: Programming Language :: Python :: 3
Classifier: Programming Language :: Python :: 3.8
Classifier: Programming Language :: Python :: 3.9
Classifier: Programming Language :: Python :: 3.10
Classifier: Programming Language :: Python :: 3.11
Classifier: Programming Language :: Python :: 3.12
Classifier: Topic :: Multimedia :: Sound/Audio :: Speech
Requires-Python: >=3.8
License-File: LICENSE
Requires-Dist: rumps>=0.4.0
Requires-Dist: pyobjc-core>=9.0
Requires-Dist: pyobjc-framework-Cocoa>=9.0
Requires-Dist: pyobjc-framework-Quartz>=9.0
Requires-Dist: pyobjc-framework-ApplicationServices>=9.0
Requires-Dist: pynput>=1.7.6
Requires-Dist: groq>=0.4.0
Requires-Dist: pyperclip>=1.8.2
Requires-Dist: pyaudio>=0.2.11
Requires-Dist: pyyaml>=6.0
Requires-Dist: numpy>=1.24.0
Requires-Dist: sounddevice>=0.4.6
Dynamic: author
Dynamic: license-file
Dynamic: requires-python
